{
  "updated": "2026-03-11",
  "count": 17,
  "items": [
    {
      "province": "国家",
      "date": "2026-01-09",
      "title": "工信部发文！3D打印纳入国家重点专项",
      "department": "工信部",
      "deadline": "2026-02-05",
      "funding": "未明确",
      "summary": "3D打印纳入国家重点专项申报，申报材料通过国家科技管理信息系统提交，系统开放时间2026年1月4日8:00，截止2月5日16:00。",
      "url": "https://www.sohu.com/a/974207399_120723807"
    },
    {
      "province": "国家",
      "date": "2025-11-12",
      "title": "智能制造系统和机器人国家科技重大专项2026年度项目申报指南",
      "department": "工信部",
      "deadline": "未明确",
      "funding": "未明确",
      "summary": "项目涉及3D打印、金属、砂型、熔模等造型工艺过程优化模型研究，支持3D打印等增材制造工艺。",
      "url": "https://kcycrawlerfile.oss-cn-beijing.aliyuncs.com/2025/11/12/%E5%B7%A5%E4%BF%A1%E5%8E%85%E9%80%9A%E8%A3%85%E5%87%BD%E3%80%942025%E3%80%95397%E5%8F%B7%E2%80%94%E9%99%84%E4%BB%B61%EF%BC%9A2026%E5%B9%B4%E5%BA%A6%E9%A1%B9%E7%9B%AE%E6%8C%87%E5%8D%97%E5%BB%BA%E8%AE%AE.pdf"
    },
    {
      "province": "国家",
      "date": "2025-12-01",
      "title": "重点新材料研发及应用国家科技重大专项2026年度项目申报",
      "department": "国家科技厅",
      "deadline": "未明确",
      "funding": "未明确",
      "summary": "国家科技重大专项重点新材料研发及应用2026年度项目申报要求通知，涉及申报和填报要求。",
      "url": "https://www.ncsti.gov.cn/kjdt/tzgg/202512/t20251201_230671.html"
    },
    {
      "province": "山东",
      "date": "2026-02-24",
      "title": "2026年度山东省创新药物和高端医疗器械申报工作",
      "department": "山东省科技厅",
      "deadline": "2026-02-28",
      "funding": "未明确",
      "summary": "山东省创新药物和高端医疗器械申报工作公示期内有异议可反映，公示期截止2026年2月28日17:00。",
      "url": "http://kjt.shandong.gov.cn/art/2026/2/24/art_13360_10323758.html"
    },
    {
      "province": "山东",
      "date": "2026-01-06",
      "title": "山东省创新药物与高端医疗器械研发补助资金申报",
      "department": "山东省科技厅",
      "deadline": "2026-02-02",
      "funding": "未明确",
      "summary": "山东省创新药物与高端医疗器械研发补助资金申报，系统1月7日开放，申报单位2月2日17:00前填报并提交至各市科技局。",
      "url": "http://kjt.shandong.gov.cn/art/2026/1/6/art_13360_10323138.html"
    },
    {
      "province": "黑龙江",
      "date": "2026-03-05",
      "title": "2026年省重点研发计划人工智能等前沿技术申报",
      "department": "黑龙江省科技厅",
      "deadline": "2026-03-16",
      "funding": "未明确",
      "summary": "黑龙江省重点研发计划人工智能等前沿技术申报，系统3月5日20:00开放，申报单位审核截止3月16日10:00。",
      "url": "https://kjt.hlj.gov.cn/kjt/c113905/202603/c00_31920573.shtml"
    },
    {
      "province": "黑龙江",
      "date": "2026-02-14",
      "title": "黑龙江省支持生物制造产业高质量发展若干政策措施",
      "department": "黑龙江省人民政府办公厅",
      "deadline": "未明确",
      "funding": "未明确",
      "summary": "黑龙江省支持生物制造产业高质量发展政策，已经省人民政府同意印发，涉及生物医学工程、生物制造相关措施。",
      "url": "https://www.hlj.gov.cn/hlj/c108373/202602/c00_31915332.shtml"
    },
    {
      "province": "湖南",
      "date": "2026-01-04",
      "title": "2026年度湖南省科技重点项目申报",
      "department": "湖南省科技厅、财政厅",
      "deadline": "未明确",
      "funding": "未明确",
      "summary": "湖南省2026年度重点项目申报，涉及医药创新，要求填写前期研究基础、研发进度和标志性成果如创新药物临床试验等。",
      "url": "https://science.hnust.edu.cn/tzgg/zknwtz/feb85e3ac391416083730388beea3914.htm"
    },
    {
      "province": "吉林",
      "date": "2025-08-29",
      "title": "吉林省科技发展计划2026年度项目申报指南",
      "department": "吉林省科技厅",
      "deadline": "未明确",
      "funding": "未明确",
      "summary": "吉林省2026年度项目申报指南，重点支持金属增材制造材料、医学植入物的3D打印PEEK材料、植入级3D打印技术标准等。",
      "url": "https://kjt.jl.gov.cn/xxgk/cwgk_84281/202508/P020250806368467467496.pdf"
    },
    {
      "province": "上海",
      "date": "2026-01-20",
      "title": "2026年度上海市生物医药创新产品攻关项目",
      "department": "上海市科学技术委员会",
      "deadline": "未明确",
      "funding": "未明确",
      "summary": "上海市2026年度生物医药创新产品攻关项目，采用网上申报方式，通过上海市科技管理信息系统进行项目申报。",
      "url": "https://stcsm.sh.gov.cn/zwgk/kyjhxm/xmsb/20260120/73e78f5e5d0e4d7ba99186e317023389.html"
    },
    {
      "province": "陕西",
      "date": "2025-11-03",
      "title": "2026年第一批省重点攻关项目方向领域",
      "department": "陕西省科技厅",
      "deadline": "2025-11-20",
      "funding": "未明确",
      "summary": "陕西省2026年第一批重点攻关项目方向领域公布，省科技厅将于2025年11月20日前发布具体项目申报指南。",
      "url": "https://news.sciencenet.cn/htmlnews/2025/11/554455.shtm"
    },
    {
      "province": "深圳",
      "date": "2025-06-10",
      "title": "2025年度深圳市重点产业研发计划",
      "department": "深圳市科技创新局",
      "deadline": "未明确",
      "funding": "未明确",
      "summary": "深圳市2025年重点产业研发计划，涵盖AI+药物研发、高端医学影像、免疫细胞治疗等前沿医学和AI医学领域。",
      "url": "https://stic.sz.gov.cn/xxgk/tzgg/content/post_12221227.html"
    },
    {
      "province": "内蒙古",
      "date": "2025-12-01",
      "title": "2026年中央引导地方科技发展专项资金项目",
      "department": "内蒙古自治区科技厅、财政厅",
      "deadline": "未明确",
      "funding": "未明确",
      "summary": "内蒙古自治区2026年中央引导地方科技发展专项资金项目征集，申报单位应为区内注册的高等院校、科研院所等。",
      "url": "http://kjt.nmg.gov.cn/kjdt/tzgg/202512/t20251201_2826228.html"
    },
    {
      "province": "广东",
      "date": "2025-11-04",
      "title": "2025年度广东省基础与应用基础研究基金企业联合基金",
      "department": "广东省科技厅",
      "deadline": "未明确",
      "funding": "未明确",
      "summary": "广东省2025年基础与应用基础研究基金支持智能医学影像融合创新联合基金，主要支持肿瘤、神经系统疾病、心血管疾病领域智能医学影像基础研究。",
      "url": "https://www.jyu.edu.cn/info/1040/43296.htm"
    },
    {
      "province": "海南",
      "date": "2025-09-23",
      "title": "2026年海南省卫生健康科技创新联合项目",
      "department": "海南省科技厅",
      "deadline": "未明确",
      "funding": "未明确",
      "summary": "海南省2026年卫生健康科技创新联合项目申报，涉及人工智能技术用于诊断、肿瘤检测等医学应用。",
      "url": "https://srd.hnhvc.edu.cn/2025/0923/c207a8862/page.htm"
    },
    {
      "province": "河南",
      "date": "2026-01-19",
      "title": "2026年度省重点研发专项备选项目库",
      "department": "河南省科技厅",
      "deadline": "未明确",
      "funding": "未明确",
      "summary": "河南省2026年重点研发专项备选项目库包含航空航天钴基高温合金增材制造、生物科技等创新项目。",
      "url": "https://xcoss.henan.gov.cn/typtfile/20260119/e6114bb413664f82a4e2d195aa82a9b8.pdf"
    },
    {
      "province": "南京",
      "date": "2025-09-20",
      "title": "2026年南京市前沿技术研发计划和科技项目预征集",
      "department": "南京市科技局",
      "deadline": "未明确",
      "funding": "未明确",
      "summary": "南京市2026年前沿技术研发计划和科技项目预征集，重点面向科技领军企业、高校院所、新型研发机构等单位。",
      "url": "https://kjj.nanjing.gov.cn/njskxjswyh/202509/P020250926596640987512.pdf"
    }
  ]
}